[
    {
        "question": "১০১। আনারসের স্লাইস প্লেইন ক্যানে ভর্তি করার সময় শতকরা কত মাত্রার চিনির গরম দ্রবণ যোগ করা হয়? [লিংকন স্যার]",
        "options": [
            "40%",
            "50%",
            "60%",
            "70%"
        ],
        "correct_option": 0,
        "explanation": "আনারসের মতো ফল কৌটাজাতকরণে সাধারণত ৪০% ঘনত্বের চিনির গরম দ্রবণ বা সিরাপ ব্যবহার করা হয়। এই সিরাপ ফলকে সংরক্ষণ করে, এর গঠন ও স্বাদ বজায় রাখে এবং ক্যানের ভেতরের বাতাস বের করে দিয়ে অক্সিডেশন রোধ করতে সাহায্য করে। [MediX]"
    },
    {
        "question": "১০২। খাদ্যবস্তু কৌটাজাতকরণের জন্য প্রয়োজনীয় তাপমাত্রা-",
        "options": [
            "40°C",
            "70°C",
            "82-100°C",
            "70-90°C"
        ],
        "correct_option": 2,
        "explanation": "খাদ্যবস্তু কৌটাজাতকরণের সময় তাপমাত্রা খাদ্যের ধরনের উপর নির্ভর করে। অ্যাসিডিক খাবারের (pH < 4.6) জন্য সাধারণত ৮২-১০০°C তাপমাত্রা প্রয়োজন হয়, যা অধিকাংশ জীবাণুকে ধ্বংস করে। স্বল্প-অ্যাসিডিক খাবারের জন্য ১২১°C তাপমাত্রার প্রয়োজন হয়। [MediX]"
    },
    {
        "question": "১০৩। পিকলিং এ ব্যবহৃত উপাদান কোনটি? [হাজারী স্যার]",
        "options": [
            "ল্যাকটিক এসিড",
            "ভিনেগার",
            "পলিফসফেট",
            "নাইট্রাইট"
        ],
        "correct_option": 1,
        "explanation": "পিকলিং বা আচার তৈরির মূল উপাদান হলো ভিনেগার (অ্যাসিটিক এসিড) বা লবণাক্ত দ্রবণ (brine)। ভিনেগারের অম্লীয় পরিবেশ অণুজীবের বৃদ্ধিকে বাধা দেয়, যা খাদ্য সংরক্ষণে সহায়তা করে। [MediX]"
    },
    {
        "question": "১০৪। তরলভর্তি কৌটাকে উত্তপ্ত করে বায়ু বা O₂ বের করার প্রক্রিয়াকে বলে- [হাজারী স্যার]",
        "options": [
            "ব্ল্যাঞ্চিং",
            "গ্রেডিং",
            "এগজস্টিং",
            "ওয়াশিং"
        ],
        "correct_option": 2,
        "explanation": "এগজস্টিং (Exhausting) হলো ক্যানিং প্রক্রিয়ার একটি ধাপ যেখানে তরল বা খাবার ভর্তি খোলা ক্যানকে উত্তপ্ত করা হয়। এর ফলে ভেতরের বাতাস ও অন্যান্য গ্যাস প্রসারিত হয়ে বেরিয়ে যায়। এরপর ক্যান সিল করা হয়, ফলে ভেতরে একটি আংশিক ভ্যাকুয়াম তৈরি হয় যা জারণ রোধ করে। [MediX]"
    },
    {
        "question": "১০৫। ক্যানের ভিতরে অধিক ব্যবহৃত ফুড লেকার কোনটি? [হাজারী স্যার]",
        "options": [
            "অ্যালুমিনিয়াম",
            "ডাইফেনলিক রেজিন",
            "ভিনাইল রেজিন",
            "ইপক্সি রেজিন"
        ],
        "correct_option": 3,
        "explanation": "খাদ্যদ্রব্যের ক্যানের ভেতরের দিকে ধাতব পাত্রের ক্ষয় রোধ করতে এবং খাদ্যকে ধাতুর সংস্পর্শ থেকে দূরে রাখতে একটি বিশেষ আস্তরণ বা লেকার ব্যবহার করা হয়। বর্তমানে ইপোক্সি রেজিন (Epoxy resin) এই কাজে সবচেয়ে বেশি ব্যবহৃত হয় কারণ এটি রাসায়নিকভাবে নিষ্ক্রিয় এবং নিরাপদ। [MediX]"
    },
    {
        "question": "১০৬। খাদ্যবস্তুর কৌটাজাতকরণের ক্ষেত্রে aₙ এর মান রাখা হয়- [হাজারী স্যার]",
        "options": [
            "০.৪ এর কম",
            "০.৬ এর বেশি",
            "০.৬ এর কম",
            "০.৪ এর বেশি"
        ],
        "correct_option": 2,
        "explanation": "কৌটাজাতকরণ বা ক্যানিং এর মূল উদ্দেশ্য হলো তাপ প্রয়োগে অণুজীব ধ্বংস করা। তবে এর সাথে সাথে চিনির সিরাপ বা লবণ দ্রবণ যোগ করে খাদ্যের ওয়াটার অ্যাক্টিভিটি (aₙ) কমানো হয়। সাধারণত aₙ এর মান ০.৬ এর নিচে নামিয়ে আনলে কোনো অণুজীবই বাড়তে পারে না। [MediX]"
    },
    {
        "question": "১০৭। ফুটন্ত পানিতে বা ফুটন্ত পানি বাষ্পে 5-10 মিনিট খাদ্যবস্তুকে সিদ্ধ করাকে কি বলে? [হাজারী স্যার]",
        "options": [
            "সিলিং",
            "এগজস্টিং",
            "ব্লাঞ্চিং",
            "রিটর্টিং"
        ],
        "correct_option": 2,
        "explanation": "ব্লাঞ্চিং (Blanching) হলো একটি প্রক্রিয়া যেখানে ফল বা সবজিকে অল্প সময়ের জন্য (সাধারণত ৫-১০ মিনিট) ফুটন্ত পানিতে বা বাষ্পে রাখা হয় এবং এরপর দ্রুত ঠান্ডা করা হয়। এটি এনজাইম নিষ্ক্রিয় করে, রঙ উজ্জ্বল রাখে এবং অণুজীবের সংখ্যা কমিয়ে আনে। [MediX]"
    },
    {
        "question": "১০৮। নিচের কোন প্রক্রিয়ায় ব্যাকটেরিয়ার স্পোর বিনষ্ট হয়? [হাজারী স্যার]",
        "options": [
            "এগজস্টিং",
            "ব্লাঞ্চিং",
            "সিলিং",
            "রিটর্টিং"
        ],
        "correct_option": 3,
        "explanation": "রিটর্টিং (Retorting) হলো ক্যানিং এর চূড়ান্ত তাপ প্রয়োগের ধাপ, যেখানে সিল করা ক্যানকে উচ্চ চাপে ও উচ্চ তাপমাত্রায় (সাধারণত ১২১°C) উত্তপ্ত করা হয়। এই شدید তাপমাত্রা ক্লস্ট্রিডিয়াম বটুলিনাম সহ সকল তাপ-প্রতিরোধী ব্যাকটেরিয়ার স্পোরকে ধ্বংস করতে সক্ষম। [MediX]"
    },
    {
        "question": "১০৯। বাঁশকোরলে কোন ভিটামিন থাকে না? [গুহ স্যার]",
        "options": [
            "C",
            "K",
            "E",
            "B"
        ],
        "correct_option": 1,
        "explanation": "বাঁশ কোরলে বিভিন্ন ধরনের ভিটামিন যেমন- ভিটামিন A, ভিটামিন B কমপ্লেক্স (বিশেষ করে B6), ভিটামিন C এবং ভিটামিন E পাওয়া যায়। তবে এতে ভিটামিন K এর উপস্থিতি উল্লেখ করার মতো নয়। [MediX]"
    },
    {
        "question": "১১০। অস্ত্রের ইমেজিং কাজে ব্যবহৃত বেরিয়াম সালফেট মিশ্রণ কোন শ্রেণিভুক্ত? [MAT: 24-25]",
        "options": [
            "কলয়েড",
            "সাসপেনশন",
            "অধঃক্ষেপ",
            "কোয়াগুলেন্ট"
        ],
        "correct_option": 1,
        "explanation": "সাসপেনশনে কণার ব্যাস >500 nm হয় এবং এটি পানিতে অদ্রবণীয়; রেখে দিলে নিচে অধঃক্ষিপ্ত হয়ে পড়ে। BaSO₄ মিশ্রণে BaSO₄ কণার ব্যাস 1-10μm এর মধ্যে, এটি পানিতে অদ্রবণীয় এবং রেখে দিলে বোতলের নিচে অধঃক্ষিপ্ত হয়। তাই এটি একটি সাসপেনশন।"
    },
    {
        "question": "১১১। সোডিয়াম ক্লোরাইড দ্রবণের বৈশিষ্ট্য কোনটি? [MAT: 24-25]",
        "options": [
            "এর কণাগুলো যে কোন মাধ্যমে দৃশ্যমান",
            "এটি টিনডাল প্রভাব দেখায়",
            "এর ব্রাউনীয় গতি আছে",
            "মিশ্রণের স্থিতি সুস্থিত"
        ],
        "correct_option": 3,
        "explanation": "সোডিয়াম ক্লোরাইড পানিতে দ্রবীভূত হয়ে একটি প্রকৃত দ্রবণ (true solution) তৈরি করে, যা সমসত্ত্ব। এর কণাগুলো (আয়ন) অদৃশ্য, টিন্ডাল প্রভাব দেখায় না এবং ব্রাউনীয় গতি প্রদর্শন করে না। প্রকৃত দ্রবণ অত্যন্ত সুস্থিত হয়, অর্থাৎ কণাগুলো কখনও থিতিয়ে পড়ে না।"
    },
    {
        "question": "১১২। সাসপেনশন এর উদাহরণ কোনটি? [DAT: 24-25]",
        "options": [
            "দুধ",
            "কর্দমাক্ত মাটি",
            "চিনির দ্রবণ",
            "রক্ত"
        ],
        "correct_option": 1,
        "explanation": "কর্দমাক্ত মাটি বা পানিতে কাদার মিশ্রণ সাসপেনশনের একটি আদর্শ উদাহরণ। এখানে মাটির কণাগুলো (কঠিন দশা) পানিতে (তরল মাধ্যম) অসমসত্ত্বভাবে ছড়িয়ে থাকে এবং স্থির অবস্থায় রাখলে মাধ্যাকর্ষণের টানে থিতিয়ে পড়ে। দুধ ও রক্ত কলয়েড, এবং চিনির দ্রবণ প্রকৃত দ্রবণ।"
    },
    {
        "question": "১১৩। নিচের কোনটি কলয়েড ইমালশন নয়? [MAT: 22-23]",
        "options": [
            "দধি",
            "দুধ",
            "মাখন",
            "শ্যাম্পু"
        ],
        "correct_option": 0,
        "explanation": "দুধ, মাখন এবং শ্যাম্পু হলো ইমালশন (emulsion) জাতীয় কলয়েড, যেখানে একটি তরল অন্য একটি অমিশ্রণীয় তরলে বিস্তৃত থাকে। দধি বা দই হলো জেল (gel) জাতীয় কলয়েড, যেখানে তরল দশা কঠিন দশার মধ্যে বিস্তৃত থাকে। [MediX]"
    },
    {
        "question": "১১৪। সবচেয়ে কার্যকর কোয়াগুলেন্ট কোনটি? [DAT: 20-21]",
        "options": [
            "KOH",
            "Fe₂(SO₄)₃",
            "Mg(NO₃)₂",
            "NaCl"
        ],
        "correct_option": 1,
        "explanation": "হার্ডি-শুলজ নীতি অনুসারে, কোয়াগুলেন্টের কার্যকারিতা এর ক্যাটায়নের চার্জের উপর নির্ভর করে। চার্জ যত বেশি, কোয়াগুলেশন ক্ষমতা তত বেশি। Fe₂(SO₄)₃ থেকে Fe³⁺ আয়ন পাওয়া যায়, যার চার্জ +3। অন্য অপশনগুলোতে ক্যাটায়নের চার্জ +1 বা +2। তাই ফেরিক সালফেট সবচেয়ে কার্যকর কোয়াগুলেন্ট। [MediX]"
    },
    {
        "question": "১১৫। নিচের কোনটি \"Milk of lime\" নামে পরিচিত? [DAT: 19-20]",
        "options": [
            "CaCO₃",
            "Ca(OH)₂",
            "NaOH, CaO",
            "CuO"
        ],
        "correct_option": 1,
        "explanation": "ক্যালসিয়াম হাইড্রোক্সাইডের (Ca(OH)₂) সম্পৃক্ত জলীয় দ্রবণকে লাইম ওয়াটার বা চুনের পানি বলে। আর পানিতে ক্যালসিয়াম হাইড্রোক্সাইডের সাসপেনশনকে মিল্ক অফ লাইম (Milk of lime) বলা হয় কারণ এর ঘোলাটে সাদা রঙ দুধের মতো দেখায়। [MediX]"
    },
    {
        "question": "১১৬। দুধ হচ্ছে এক প্রকার- [MAT: 17-18]",
        "options": [
            "জেল",
            "কলয়েড (সল)",
            "ইমালসন",
            "সাসপেনশন"
        ],
        "correct_option": 2,
        "explanation": "দুধ হলো একটি ইমালশন। এটি তেল-ইন-ওয়াটার (oil-in-water) ধরনের কলয়েড, যেখানে চর্বির ক্ষুদ্র কণা (তেল/কঠিন দশা) পানিতে (জলীয় দশা) বিস্তৃত থাকে এবং ক্যাসিন নামক প্রোটিন ইমালসিফায়ার হিসেবে কাজ করে। [MediX]"
    },
    {
        "question": "১১৭। পানিতে ময়দার মিশ্রণকে কী বলে? [হাজারী স্যার]",
        "options": [
            "দ্রবণ",
            "কলয়েড",
            "কোয়াগুলেশন",
            "সাসপেনশন"
        ],
        "correct_option": 1,
        "explanation": "পানিতে ময়দার (শ্বেতসার) মিশ্রণ একটি কলয়েডাল দ্রবণ তৈরি করে। এখানে শ্বেতসারের কণাগুলোর আকার ১ থেকে ৫০০ ন্যানোমিটারের মধ্যে থাকে, যা প্রকৃত দ্রবণ এবং সাসপেনশনের কণার আকারের মাঝামাঝি। [MediX]"
    },
    {
        "question": "১১৮। পেপটাইজেশন পদ্ধতিতে তৈরি করা যায়- [হাজারী স্যার]",
        "options": [
            "ইমালশন",
            "কলয়েড",
            "সাসপেনশন",
            "কোয়াগুলেশন"
        ],
        "correct_option": 1,
        "explanation": "পেপটাইজেশন বা অপলয়ন হলো এমন একটি প্রক্রিয়া যার মাধ্যমে কোনো সদ্য প্রস্তুত অধঃক্ষেপকে উপযুক্ত তড়িৎ বিশ্লেষ্য (পেপটাইজিং এজেন্ট) যোগ করে কলয়েডাল দ্রবণে রূপান্তরিত করা হয়। [MediX]"
    },
    {
        "question": "১১৯। সাসপেনশন কী? [কবীর স্যার]",
        "options": [
            "সমসত্ত্ব মিশ্রণ",
            "অসমসত্ত্ব মিশ্রণ",
            "তরল-তরল মিশ্রণ",
            "তরল-তরল দ্রবণ"
        ],
        "correct_option": 1,
        "explanation": "সাসপেনশন হলো একটি অসমসত্ত্ব মিশ্রণ যেখানে কঠিন কণাগুলো (ব্যাস > 500 nm) একটি তরল মাধ্যমে অস্থায়ীভাবে ভাসমান থাকে কিন্তু সময়ের সাথে সাথে থিতিয়ে পড়ে। যেমন: পানিতে বালির মিশ্রণ। [MediX]"
    },
    {
        "question": "১২০। অ্যারোসল সাসপেনশন হলে এর বিস্তার মাধ্যম কোনটি? [কবীর স্যার]",
        "options": [
            "গ্যাস",
            "তরল",
            "কঠিন",
            "গ্যাস ও তরলের মিশ্রণ"
        ],
        "correct_option": 0,
        "explanation": "অ্যারোসল হলো এক ধরনের কলয়েড যেখানে বিস্তার মাধ্যম হলো গ্যাস। বিস্তৃত দশা কঠিন বা তরল হতে পারে। যদি বিস্তৃত দশা কঠিন হয় (যেমন- ধোঁয়া) বা তরল হয় (যেমন- কুয়াশা, মেঘ), উভয় ক্ষেত্রেই এটি অ্যারোসল। [MediX]"
    },
    {
        "question": "১২১। Mg(OH)₂ এবং পানির মিশ্রণকে কী বলা যায়? [কবীর স্যার]",
        "options": [
            "সাসপেনশন",
            "কলয়েড",
            "ইমালশন",
            "দ্রবণ"
        ],
        "correct_option": 0,
        "explanation": "ম্যাগনেসিয়াম হাইড্রোক্সাইড [Mg(OH)₂] পানিতে খুবই সামান্য দ্রবণীয়। তাই পানিতে এর মিশ্রণ একটি সাসপেনশন তৈরি করে, যা 'মিল্ক অফ ম্যাগনেসিয়া' নামে পরিচিত। এটি অ্যান্টাসিড হিসেবে ব্যবহৃত হয়। [MediX]"
    },
    {
        "question": "১২২। নিচের কোন আয়নটির কোয়াগুলেশন ক্ষমতা সবচেয়ে বেশি? [কবীর স্যার]",
        "options": [
            "Al³⁺",
            "Cu²⁺",
            "Mg²⁺",
            "K⁺"
        ],
        "correct_option": 0,
        "explanation": "হার্ডি-শুলজ সূত্রানুযায়ী, কোনো আয়নের তঞ্চন বা কোয়াগুলেশন ক্ষমতা তার চার্জের সমানুপাতিক। এখানে Al³⁺ এর চার্জ (+3) সর্বোচ্চ হওয়ায় এর কোয়াগুলেশন ক্ষমতা সবচেয়ে বেশি। ক্ষমতার ক্রম: Al³⁺ > Cu²⁺ ≈ Mg²⁺ > K⁺। [MediX]"
    },
    {
        "question": "১২৩। কোয়াগুলেন্ট হিসেবে কার্যকারিতার ক্রম- [কবীর স্যার]",
        "options": [
            "Na⁺ > Ba²⁺ > Al³⁺",
            "Ba²⁺ > Na⁺ > Al³⁺",
            "Al³⁺ > Ba²⁺ > Na⁺",
            "Ba²⁺ > Al³⁺ > Na⁺"
        ],
        "correct_option": 2,
        "explanation": "হার্ডি-শুলজ সূত্র অনুসারে, ক্যাটায়নের চার্জ যত বৃদ্ধি পায়, ঋণাত্মক সলকে জমাট বাঁধানোর ক্ষমতা তত বৃদ্ধি পায়। সুতরাং, কার্যকারিতার সঠিক ক্রম হলো: Al³⁺ > Ba²⁺ > Na⁺। [MediX]"
    },
    {
        "question": "১২৪। কোয়াগুলেশন পদ্ধতি কোনটি? [কবীর স্যার]",
        "options": [
            "দুধ থেকে ছানা তৈরি",
            "As₂S₃ সল-এ NaCl যোগ করলে অধঃক্ষেপ পড়ে",
            "মাখন থেকে ঘি তৈরি",
            "চিনির গাঢ় তপ্ত দ্রবণকে শীতল করলে চিনির দানা তৈরি হয়"
        ],
        "correct_option": 0,
        "explanation": "কোয়াগুলেশন বা তঞ্চন হলো কলয়েড কণাগুলোর একত্রিত হয়ে থিতিয়ে পড়ার প্রক্রিয়া। দুধে লেবুর রস বা ভিনেগার যোগ করলে দুধের প্রোটিন কণাগুলো জমাট বেঁধে ছানায় পরিণত হয়, যা কোয়াগুলেশনের একটি উৎকৃষ্ট উদাহরণ। [MediX]"
    },
    {
        "question": "১২৫। অ্যারোসলে নিম্নের কোন যৌগটি ব্যবহার করা হয়? [গুহ স্যার]",
        "options": [
            "ওজোন",
            "গ্যামাক্সিন",
            "ফ্রেওন",
            "ট্রাই ওক্রোন"
        ],
        "correct_option": 2,
        "explanation": "ফ্রেওন (Freon) হলো ক্লোরোফ্লুরোকার্বনের (CFC) বাণিজ্যিক নাম। এটি পূর্বে অ্যারোসল স্প্রে-তে প্রোপেল্যান্ট বা চালক গ্যাস হিসেবে বহুল ব্যবহৃত হতো। তবে ওজোন স্তর ক্ষয়ের জন্য দায়ী হওয়ায় এর ব্যবহার এখন নিয়ন্ত্রিত। [MediX]"
    },
    {
        "question": "১২৬। কোনটি উত্তম কোয়াগুলেন্ট? [গুহ স্যার]",
        "options": [
            "Na⁺",
            "Mg²⁺",
            "Ba²⁺",
            "Al³⁺"
        ],
        "correct_option": 3,
        "explanation": "হার্ডি-শুলজ নীতি অনুযায়ী, আয়নের চার্জ যত বেশি, তার কোয়াগুলেশন বা তঞ্চন ক্ষমতা তত বেশি। প্রদত্ত আয়নগুলোর মধ্যে Al³⁺ এর চার্জ (+3) সর্বোচ্চ, তাই এটি সবচেয়ে উত্তম কোয়াগুলেন্ট। [MediX]"
    },
    {
        "question": "১২৭। কলয়েড কণাগুলোকে কোন পদ্ধতিতে আলাদা করা যেতে পারে? [লিংকন স্যার]",
        "options": [
            "ফিল্ট্রেশন",
            "আল্ট্রাফিল্ট্রেশন",
            "মেমব্রেন",
            "পরিস্রাবণ"
        ],
        "correct_option": 1,
        "explanation": "সাধারণ ফিল্টার কাগজের ছিদ্র কলয়েড কণার চেয়ে বড় হওয়ায় এদের আলাদা করা যায় না। কলয়েড কণাগুলোকে দ্রাবক থেকে আলাদা করার জন্য বিশেষ ধরনের ঝিল্লি বা মেমব্রেন ব্যবহার করে যে পরিস্রাবণ করা হয়, তাকে আল্ট্রাফিল্ট্রেশন বলে। [MediX]"
    },
    {
        "question": "১২৮। নিম্নের কোনটি মিশ্রণ নয়? [লিংকন স্যার]",
        "options": [
            "সমুদ্রের পানি",
            "বায়ু",
            "কাদামাটি",
            "প্রোপেন-1, 2, 3-ট্রাইঅল"
        ],
        "correct_option": 3,
        "explanation": "প্রোপেন-1, 2, 3-ট্রাইঅল, যা গ্লিসারিন নামেও পরিচিত, একটি বিশুদ্ধ রাসায়নিক যৌগ (C₃H₈O₃)। অন্যদিকে, সমুদ্রের পানি (লবণ ও পানির মিশ্রণ), বায়ু (বিভিন্ন গ্যাসের মিশ্রণ), এবং কাদামাটি (মাটি ও পানির মিশ্রণ) হলো মিশ্রণ। [MediX]"
    },
    {
        "question": "১২৯। কলয়েড কণার আকৃতি (ব্যাস) কত? [লিংকন স্যার]",
        "options": [
            "0.1 ~ 2.0 nm",
            "2.0 ~ 500 nm",
            "500 ~ 700 nm",
            "≥ 700 nm"
        ],
        "correct_option": 1,
        "explanation": "কলয়েড কণার ব্যাস সাধারণত ২ থেকে ৫০০ ন্যানোমিটার (nm) এর মধ্যে থাকে। এটি প্রকৃত দ্রবণের কণার ( < 2 nm) চেয়ে বড় কিন্তু সাসপেনশনের কণার ( > 500 nm) চেয়ে ছোট। [MediX]"
    },
    {
        "question": "১৩০। টিনডাল প্রভাব নিচের কোনটির সাথে সম্পর্কযুক্ত? [হাজারী স্যার]",
        "options": [
            "সল",
            "জেল",
            "কলয়েড",
            "ক্রিস্টালয়েড"
        ],
        "correct_option": 2,
        "explanation": "টিন্ডাল প্রভাব কলয়েড দ্রবণের একটি স্বতন্ত্র বৈশিষ্ট্য। কলয়েড কণাগুলো যথেষ্ট বড় হওয়ায় এরা আলোর রশ্মিকে বিচ্ছুরিত করতে পারে, ফলে দ্রবণের মধ্য দিয়ে আলোর গতিপথ দৃশ্যমান হয়। সল ও জেল উভয়ই কলয়েডের প্রকারভেদ। [MediX]"
    },
    {
        "question": "১৩১। কোল্ড ক্রিম হল- [হাজারী স্যার]",
        "options": [
            "Water in oil suspension",
            "Oil in water emulsion",
            "Water in oil emulsion",
            "Oil in water suspension"
        ],
        "correct_option": 2,
        "explanation": "কোল্ড ক্রিম হলো পানি-ইন-তেল (Water-in-oil) ধরনের ইমালশন। এখানে পানির (কম পরিমাণে) কণাগুলো তেলের (বেশি পরিমাণে) মধ্যে বিস্তৃত থাকে। এটি ত্বকে শীতল অনুভূতি দেয় কারণ পানি ধীরে ধীরে বাষ্পীভূত হয়। [MediX]"
    },
    {
        "question": "১৩২। নিচের কোনটি সাসপেনশনের উদাহরণ নয়? [হাজারী স্যার]",
        "options": [
            "কলেরা ভ্যাকসিন",
            "ক্যালামাইন লোশন",
            "হিমোগ্লোবিন",
            "রক্ত"
        ],
        "correct_option": 2,
        "explanation": "রক্ত, কলেরা ভ্যাকসিন এবং ক্যালামাইন লোশন সাসপেনশনের উদাহরণ। হিমোগ্লোবিন হলো একটি প্রোটিন অণু যা রক্তের লোহিত রক্তকণিকায় থাকে, এটি নিজে কোনো সাসপেনশন নয়। এটি একটি কলয়েডাল আকারের ম্যাক্রোমলিকিউল। [MediX]"
    },
    {
        "question": "১৩৩। নিচের কোনটি জেল এর উদাহরণ? [হাজারী স্যার]",
        "options": [
            "দুধ",
            "ক্রিম",
            "পনির",
            "শ্যাম্পু"
        ],
        "correct_option": 2,
        "explanation": "জেল হলো এক ধরনের কলয়েড যেখানে তরল দশা একটি কঠিন মাধ্যমের মধ্যে আবদ্ধ থাকে। পনির, দই, জেলি ইত্যাদি জেলের উদাহরণ। এখানে তরল (জলীয় অংশ) কঠিন প্রোটিন (ক্যাসিন) নেটওয়ার্কের মধ্যে আটকে থাকে। [MediX]"
    },
    {
        "question": "১৩৪। যদি কোনো কঠিন বস্তু কণা অন্য ফেজ এ বণ্টিত হয়ে কলয়েড গঠন করে তার নাম কী? [কবীর স্যার]",
        "options": [
            "সল",
            "জেল",
            "তেল",
            "ইমালশন"
        ],
        "correct_option": 0,
        "explanation": "যখন কঠিন কণা (বিস্তৃত দশা) একটি তরল মাধ্যমে (বিস্তার মাধ্যম) ছড়িয়ে থেকে কলয়েড গঠন করে, তখন তাকে 'সল' (Sol) বলা হয়। যেমন: গোল্ড সল, স্টার্চ সল। [MediX]"
    },
    {
        "question": "১৩৫। ইলেকট্রোলাইটের উপস্থিতিতে আণবিক পর্যায়ের অসংখ্য কণার একত্রিত হয়ে জমাট বাঁধার প্রক্রিয়াকে কী বলে? [কবীর স্যার]",
        "options": [
            "সাসপেনশন",
            "কলয়েড",
            "কোয়াগুলেশন",
            "ইমালশন"
        ],
        "correct_option": 2,
        "explanation": "কোয়াগুলেশন বা তঞ্চন হলো এমন একটি প্রক্রিয়া যেখানে তড়িৎ বিশ্লেষ্য (ইলেকট্রোলাইট) যোগ করার ফলে কলয়েড কণাগুলো তাদের চার্জ হারিয়ে ফেলে এবং একত্রিত হয়ে বড় কণায় পরিণত হয়ে থিতিয়ে পড়ে। [MediX]"
    },
    {
        "question": "১৩৬। সংগৃহীত দুধের pH নিয়ন্ত্রণে কোনটি ব্যবহৃত হয়? [MAT: 24-25]",
        "options": [
            "KHCO₃",
            "Na₂CO₃",
            "NaHCO₃",
            "H₂O"
        ],
        "correct_option": 2,
        "explanation": "দুধ সংগ্রহের পর ল্যাকটিক এসিড তৈরির কারণে এর pH কমতে শুরু করে (অম্লীয় হয়)। দুধের pH মান ৬.৬-৬.৯ এর মধ্যে নিয়ন্ত্রণের জন্য অল্প পরিমাণে সোডিয়াম বাইকার্বনেট (NaHCO₃) বা সোডিয়াম কার্বনেট (Na₂CO₃) দ্রবণ যোগ করা হয়, যা মৃদু ক্ষার হিসেবে কাজ করে।"
    },
    {
        "question": "১৩৭। কোন প্রক্রিয়া দুধ থেকে ছানা (curdled milk) তৈরি করে? [MAT: 22-23; DAT: 17-18, 16-17]",
        "options": [
            "অক্সিডেশন",
            "ফারমেনটেশন",
            "কোয়াগুলেশন",
            "আর্দ্র বিশ্লেষণ"
        ],
        "correct_option": 2,
        "explanation": "দুধে অম্ল (যেমন লেবুর রস) যোগ করলে বা ব্যাকটেরিয়া দ্বারা ল্যাকটিক এসিড তৈরি হলে দুধের প্রোটিন ক্যাসিনের কোয়াগুলেশন বা তঞ্চন ঘটে। এতে ক্যাসিন কণাগুলো জমাট বেঁধে ছানায় পরিণত হয়। [MediX]"
    },
    {
        "question": "১৩৮। দুধে নিচের কোন disaccharide টি থাকে? [MAT: 20-21]",
        "options": [
            "Sucrose",
            "Cellulose",
            "Lactose",
            "Maltose"
        ],
        "correct_option": 2,
        "explanation": "দুধে উপস্থিত প্রধান শর্করা হলো ল্যাকটোজ (Lactose)। এটি একটি ডাইস্যাকারাইড যা এক অণু গ্লুকোজ এবং এক অণু গ্যালাকটোজ দ্বারা গঠিত। একে মিল্ক সুগারও বলা হয়। [MediX]"
    },
    {
        "question": "১৩৯। নিচের কোন স্তন্যপায়ী প্রাণির দুগ্ধে ল্যাকটোজ সবচেয়ে বেশি থাকে? [DAT: 20-21]",
        "options": [
            "মানুষ",
            "মহিষ",
            "ছাগল",
            "গরু"
        ],
        "correct_option": 0,
        "explanation": "স্তন্যপায়ী প্রাণীদের মধ্যে মানুষের দুধে ল্যাকটোজের পরিমাণ সবচেয়ে বেশি থাকে, যা প্রায় ৭%। এটি শিশুর মস্তিষ্কের বিকাশে সহায়তা করে। গরুর দুধে ল্যাকটোজের পরিমাণ প্রায় ৪.৮%। [MediX]"
    },
    {
        "question": "১৪০। কোন প্রাণীর দুধে শক্তি (ক্যালরি) সবচেয়ে বেশি? [হাজারী স্যার]",
        "options": [
            "গাভী",
            "মহিষ",
            "ছাগল",
            "ভেড়া"
        ],
        "correct_option": 1,
        "explanation": "মহিষের দুধে চর্বি বা ফ্যাটের পরিমাণ (প্রায় ৭-৮%) গরুর দুধের (প্রায় ৩-৪%) চেয়ে অনেক বেশি। যেহেতু ফ্যাট থেকে সবচেয়ে বেশি ক্যালরি পাওয়া যায়, তাই মহিষের দুধের ক্যালরি মান (প্রায় ১০০ kcal/100g) সবচেয়ে বেশি। [MediX]"
    },
    {
        "question": "১৪১। দুধের প্রধান প্রোটিন কোনটি? [হাজারী স্যার]",
        "options": [
            "ক্যারোটিন",
            "লিপিড",
            "ক্যাসিন",
            "ল্যাকটালবুমিন"
        ],
        "correct_option": 2,
        "explanation": "দুধের মোট প্রোটিনের প্রায় ৮০-৮২% হলো ক্যাসিন (Casein)। এটি একটি ফসফোপ্রোটিন যা দুধে কলয়েডাল সাসপেনশন আকারে থাকে এবং দুধের সাদা রঙের জন্য দায়ী। ছানা তৈরির মূল উপাদানই হলো ক্যাসিন। [MediX]"
    },
    {
        "question": "১৪২। দুধে নিচের কোন আয়নসমূহের সেটটি অধিক পরিমাণে বর্তমান থাকে? [হাজারী স্যার]",
        "options": [
            "K⁺, Ca²⁺, Cl⁻",
            "Ca²⁺, Mg²⁺, Fe³⁺",
            "K⁺, Cu²⁺, P³⁻",
            "Na⁺, K⁺, Cl⁻"
        ],
        "correct_option": 0,
        "explanation": "দুধে বিভিন্ন খনিজ লবণ আয়ন হিসেবে থাকে। এর মধ্যে ক্যালসিয়াম (Ca²⁺), পটাসিয়াম (K⁺), ফসফেট (PO₄³⁻), এবং ক্লোরাইড (Cl⁻) সবচেয়ে বেশি পরিমাণে থাকে। এই আয়নগুলো দুধের পুষ্টিগুণ এবং স্থিতিশীলতার জন্য গুরুত্বপূর্ণ। [MediX]"
    },
    {
        "question": "১৪৩। নিচের কোন প্রাণির দুধে প্রোটিনের পরিমাণ সবচেয়ে বেশি থাকে? [হাজারী স্যার]",
        "options": [
            "মানুষ",
            "গরু",
            "মহিষ",
            "ভেড়ী"
        ],
        "correct_option": 3,
        "explanation": "ভেড়ীর (Ewe) দুধে প্রোটিনের পরিমাণ সবচেয়ে বেশি, প্রায় ৫.৫% থেকে ৬%। এরপরেই রয়েছে মহিষ (৩.৮%) ও গরু (৩.২%)। মানুষের দুধে প্রোটিনের পরিমাণ তুলনামূলকভাবে কম (প্রায় ১.১%)। [MediX]"
    },
    {
        "question": "১৪৪। নিচের কোন প্রাণির দুধে চর্বির পরিমাণ সবচেয়ে বেশি থাকে? [হাজারী স্যার]",
        "options": [
            "গরু",
            "মহিষ",
            "ছাগল",
            "মানুষ"
        ],
        "correct_option": 1,
        "explanation": "প্রদত্ত প্রাণীগুলোর মধ্যে মহিষের দুধে চর্বির পরিমাণ সবচেয়ে বেশি, প্রায় ৭% থেকে ৮%। এই উচ্চ চর্বির কারণেই মহিষের দুধ থেকে মাখন ও ঘি বেশি পরিমাণে উৎপন্ন হয়। [MediX]"
    },
    {
        "question": "১৪৫। তরল দুধ সংরক্ষণে কোন পদ্ধতি অবলম্বন করা হয়? [হাজারী স্যার]",
        "options": [
            "হিমায়ন",
            "কৌটাজাতকরণ",
            "পাস্তুরাইজিং",
            "ভিনেগার ব্যবহার"
        ],
        "correct_option": 2,
        "explanation": "তরল দুধ স্বল্প সময়ের জন্য সংরক্ষণের সবচেয়ে প্রচলিত পদ্ধতি হলো পাস্তুরাইজেশন বা পাস্তুরায়ন। এই পদ্ধতিতে দুধকে নির্দিষ্ট তাপমাত্রায় উত্তপ্ত করে দ্রুত ঠান্ডা করা হয়, যা রোগ সৃষ্টিকারী ব্যাকটেরিয়াকে ধ্বংস করে কিন্তু দুধের পুষ্টিগুণ অক্ষুণ্ণ রাখে। [MediX]"
    },
    {
        "question": "১৪৬। মাখনকে পানিমুক্ত করা হয় কোন পদ্ধতিতে? [হাজারী স্যার]",
        "options": [
            "পানি শোষণ করে",
            "মাখনকে চাপ দিয়ে দলিত করে",
            "মাখনে P₂O₅ যোগ করে",
            "মাখনে CaO যোগ করে"
        ],
        "correct_option": 1,
        "explanation": "মাখন তৈরির সময় এটিকে ভালোভাবে ধৌত করা হয় এবং চাপ দিয়ে বা মন্থন করে অতিরিক্ত পানি (বাটারমিল্ক) বের করে দেওয়া হয়। এই প্রক্রিয়াকে 'ওয়ার্কিং' (working) বলা হয়, যা মাখনের গঠনকে মসৃণ করে এবং পানিমুক্ত করে এর সংরক্ষণকাল বাড়ায়। [MediX]"
    },
    {
        "question": "১৪৭। কোনটি দুধের মিষ্টতা বাড়ায়? [হাজারী স্যার]",
        "options": [
            "সায়ট্রেট",
            "খনিজ লবণ",
            "প্রোটিন",
            "ল্যাকটোজ"
        ],
        "correct_option": 3,
        "explanation": "দুধের হালকা মিষ্টি স্বাদের জন্য দায়ী হলো এতে উপস্থিত শর্করা ল্যাকটোজ (Lactose)। একে 'মিল্ক সুগার'ও বলা হয়। ল্যাকটোজের কারণেই দুধের স্বাদ মিষ্টি হয়। [MediX]"
    },
    {
        "question": "১৪৮। গাভীর দুধে খাদ্য ক্যালরি (kcal/100g) কত? [হাজারী স্যার]",
        "options": [
            "৮৭.২",
            "৬৬",
            "৭০",
            "১০২"
        ],
        "correct_option": 1,
        "explanation": "গাভীর দুধে চর্বি, প্রোটিন ও শর্করার পরিমাণের উপর ভিত্তি করে এর ক্যালরি মান নির্ধারিত হয়। প্রতি ১০০ গ্রাম গাভীর দুধে প্রায় ৬৬ কিলোক্যালরি (kcal) শক্তি থাকে। [MediX]"
    },
    {
        "question": "১৪৯। শতকরা হিসাবে দুধের প্রধান উপাদান কোনটি? [হাজারী স্যার]",
        "options": [
            "চর্বি",
            "আমিষ",
            "শর্করা",
            "পানি"
        ],
        "correct_option": 3,
        "explanation": "দুধের শতকরা হিসাবে প্রধান উপাদান হলো পানি। গাভীর দুধে প্রায় ৮৭% পানি থাকে। পানির পরেই অন্যান্য উপাদান যেমন ল্যাকটোজ (শর্করা), ফ্যাট (চর্বি) এবং প্রোটিন (আমিষ) থাকে। [MediX]"
    },
    {
        "question": "১৫০। গাভীর দুধে কত % পানি থাকে? [হাজারী স্যার]",
        "options": [
            "78.2",
            "80.2",
            "87.2",
            "90.2"
        ],
        "correct_option": 2,
        "explanation": "গাভীর দুধের সিংহভাগই হলো পানি। এর সংযুতি অনুসারে, গাভীর দুধে গড়ে প্রায় ৮৭.২% পানি থাকে। এই পানি অন্যান্য পুষ্টি উপাদানগুলোকে দ্রবীভূত বা ভাসমান রাখে। [MediX]"
    },
    {
        "question": "১৫১। সর্বোচ্চ শক্তি পাওয়া যায় নিম্নের কোন খাদ্যটি থেকে? [কবীর স্যার]",
        "options": [
            "মাখন",
            "ডিম",
            "দুধ",
            "চিনি"
        ],
        "correct_option": 0,
        "explanation": "প্রতি গ্রাম ফ্যাট থেকে প্রায় ৯ কিলোক্যালরি শক্তি পাওয়া যায়, যা শর্করা বা প্রোটিনের (প্রায় ৪ কিলোক্যালরি/গ্রাম) দ্বিগুণেরও বেশি। মাখনে প্রায় ৮০% ফ্যাট থাকে, তাই প্রদত্ত খাদ্যগুলোর মধ্যে মাখন থেকে একক ভরে সর্বোচ্চ শক্তি পাওয়া যায়। [MediX]"
    },
    {
        "question": "১৫২। দুধে কয় ধরনের ক্যাসিন থাকে? [কবীর স্যার]",
        "options": [
            "২",
            "৩",
            "৪",
            "৫"
        ],
        "correct_option": 2,
        "explanation": "দুধের প্রধান প্রোটিন ক্যাসিন মূলত চারটি ভিন্ন ধরনের পলিপেপটাইড চেইন দ্বারা গঠিত। এগুলো হলো: আলফা-এস১ (αs1), আলফা-এস২ (αs2), বিটা (β), এবং কাপ্পা (κ) ক্যাসিন। [MediX]"
    },
    {
        "question": "১৫৩। দুধে প্রাকৃতিক ইমালসিফায়ার হিসেবে কোনটি থাকে? [কবীর স্যার]",
        "options": [
            "ল্যাক্টোজ",
            "চর্বি",
            "প্রোটিন",
            "গ্যালাক্টোজ"
        ],
        "correct_option": 2,
        "explanation": "দুধে চর্বির কণাগুলো পানিতে ভাসমান থাকে কারণ দুধের প্রোটিন, বিশেষ করে ক্যাসিন, প্রাকৃতিক ইমালসিফায়ার হিসেবে কাজ করে। প্রোটিন অণুগুলো চর্বির কণার চারপাশে একটি আবরণ তৈরি করে, যা কণাগুলোকে একত্রিত হতে বাধা দেয়। [MediX]"
    },
    {
        "question": "১৫৪। কোনটি প্রোটিন? [কবীর স্যার]",
        "options": [
            "ক্যাসিন",
            "ল্যাকটোজ",
            "সাইট্রিক এসিড",
            "BHT"
        ],
        "correct_option": 0,
        "explanation": "ক্যাসিন (Casein) হলো দুধে প্রাপ্ত প্রধান প্রোটিন। ল্যাকটোজ একটি শর্করা, সাইট্রিক এসিড একটি জৈব এসিড এবং BHT একটি কৃত্রিম অ্যান্টিঅক্সিডেন্ট। [MediX]"
    },
    {
        "question": "১৫৫। রাসায়নিক সংযুক্তির দিক থেকে একই কোন যুগল? [কবীর স্যার]",
        "options": [
            "দুধ ও মাখন",
            "মাখন ও ঘি",
            "গ্লাস ক্লিনার ও টয়লেট ক্লিনার",
            "সাবান ও ডিটারজেন্ট"
        ],
        "correct_option": 1,
        "explanation": "মাখনকে জ্বাল দিয়ে পানি এবং কঠিন উপাদান (দুধের প্রোটিন) দূর করলে বিশুদ্ধ চর্বি বা ফ্যাট পাওয়া যায়, যাকে ঘি বলা হয়। তাই রাসায়নিকভাবে মাখন এবং ঘি প্রায় একই উপাদান (মিল্ক ফ্যাট) দ্বারা গঠিত, যদিও তাদের অনুপাত ভিন্ন। [MediX]"
    },
    {
        "question": "১৫৬। মাখনে চর্বি ও পানির অনুপাত কত? [গুহ স্যার]",
        "options": [
            "80:18",
            "20:80",
            "28:72",
            "60:40"
        ],
        "correct_option": 0,
        "explanation": "মাখনের প্রধান উপাদান হলো মিল্ক ফ্যাট বা চর্বি। আদর্শগতভাবে, মাখনে প্রায় ৮০% চর্বি, ১৬-১৮% পানি এবং বাকি অংশটুকু মিল্ক সলিড (প্রোটিন, লবণ) থাকে। সুতরাং, চর্বি ও পানির অনুপাত প্রায় ৮০:১৮। [MediX]"
    },
    {
        "question": "১৫৭। গরুর দুধে চর্বির শতকরা পরিমাণ- [লিংকন স্যার]",
        "options": [
            "1.1-3.1",
            "3.5-4.5",
            "4.6-6.8",
            "7.0-8.5"
        ],
        "correct_option": 1,
        "explanation": "গরুর জাত, খাদ্য এবং পারিপার্শ্বিক অবস্থার উপর নির্ভর করে দুধে চর্বির পরিমাণ পরিবর্তিত হয়। তবে গড়ে, গরুর দুধে চর্বির শতকরা পরিমাণ প্রায় ৩.৫% থেকে ৪.৫% এর মধ্যে থাকে। [MediX]"
    },
    {
        "question": "১৫৮। দুধকে সংরক্ষণের জন্য কত °C তাপমাত্রা দরকার? [হাজারী স্যার]",
        "options": [
            "১০°",
            "১৫°",
            "২৫°",
            "৩০°"
        ],
        "correct_option": 0,
        "explanation": "দুধকে স্বল্প সময়ের জন্য সংরক্ষণের জন্য রেফ্রিজারেটরে রাখা হয়। ৪°C বা তার কম তাপমাত্রা সবচেয়ে ভালো, তবে ১০°C এর নিচে রাখলেও ব্যাকটেরিয়ার বৃদ্ধি অনেকখানি ধীর হয়ে যায়। ২৫-৩০°C তাপমাত্রা ব্যাকটেরিয়ার বৃদ্ধির জন্য সহায়ক। [MediX]"
    },
    {
        "question": "১৫৯। মায়ের বুকের দুধে পানির শতকরা পরিমাণ কত? [হাজারী স্যার]",
        "options": [
            "87.3",
            "87.1",
            "87.6",
            "87.8"
        ],
        "correct_option": 2,
        "explanation": "মায়ের বুকের দুধের প্রায় ৮৭.৬% হলো পানি। এই পানি শিশুর ದೇಹকে হাইড্রেটেড রাখে এবং অন্যান্য পুষ্টি উপাদানগুলোকে দ্রবীভূত করে শিশুর শরীরে পৌঁছে দেয়। [MediX]"
    },
    {
        "question": "১৬০। দুধে কোন ভিটামিন বেশি পরিমাণে থাকে? [হাজারী স্যার]",
        "options": [
            "Vit-A",
            "Vit-C",
            "Vit-D",
            "Vit-E"
        ],
        "correct_option": 0,
        "explanation": "দুধ এবং দুগ্ধজাত খাবার ভিটামিন A এবং ভিটামিন D (ফর্টিফাইড হলে) এর ভালো উৎস। দুধের চর্বিতে ভিটামিন A দ্রবীভূত থাকে, যা দৃষ্টিশক্তি এবং রোগ প্রতিরোধ ক্ষমতার জন্য জরুরি। [MediX]"
    },
    {
        "question": "১৬১। দুধে হোয়ে (Whey) প্রোটিনের শতকরা পরিমাণ কতভাগ? [হাজারী স্যার]",
        "options": [
            "১০",
            "১৫",
            "১৮",
            "২৫"
        ],
        "correct_option": 2,
        "explanation": "দুধের মোট প্রোটিনের প্রায় ১৮-২০% হলো হোয়ে (Whey) প্রোটিন। ছানা তৈরির সময় ক্যাসিন জমাট বেঁধে যায় এবং অবশিষ্ট জলীয় অংশকে হোয়ে বা ঘোল বলে, যাতে এই প্রোটিন দ্রবীভূত থাকে। [MediX]"
    },
    {
        "question": "১৬২। প্রতি 100 ml গো-দুধে কত % প্রোটিন থাকে? [হাজারী স্যার]",
        "options": [
            "4.6",
            "1.5",
            "0.9",
            "3.2"
        ],
        "correct_option": 3,
        "explanation": "প্রতি ১০০ মিলি বা গ্রাম গরুর দুধে গড়ে প্রায় ৩.২ গ্রাম প্রোটিন থাকে। অর্থাৎ, প্রোটিনের শতকরা পরিমাণ প্রায় ৩.২%। [MediX]"
    },
    {
        "question": "১৬৩। মানুষের 100 ml দুধে প্রোটিনের পরিমাণ- [হাজারী স্যার]",
        "options": [
            "1.1%",
            "4.2%",
            "7%",
            "0.9%"
        ],
        "correct_option": 0,
        "explanation": "গরুর দুধের তুলনায় মানুষের দুধে প্রোটিনের পরিমাণ কম। প্রতি ১০০ মিলি মানুষের দুধে প্রোটিনের পরিমাণ প্রায় ১.১%। তবে এই প্রোটিন শিশুর জন্য অত্যন্ত সহজপাচ্য। [MediX]"
    },
    {
        "question": "১৬৪। দুধের প্রোটিনের শতকরা কতভাগ ক্যাসিন? [হাজারী স্যার]",
        "options": [
            "৬০",
            "৭০",
            "৮২",
            "৭৫"
        ],
        "correct_option": 2,
        "explanation": "দুধের মোট প্রোটিনের একটি বড় অংশই হলো ক্যাসিন। গড়ে, দুধের মোট প্রোটিনের প্রায় ৮২% হলো ক্যাসিন এবং বাকি ১৮% হলো হোয়ে প্রোটিন। [MediX]"
    },
    {
        "question": "১৬৫। মাখন কোন ভিটামিনের উৎকৃষ্ট উৎস? [হাজারী স্যার]",
        "options": [
            "Vit - E",
            "Vit - K",
            "Vit - A",
            "Vit - D"
        ],
        "correct_option": 2,
        "explanation": "মাখন যেহেতু মিল্ক ফ্যাট বা দুধের চর্বি থেকে তৈরি হয়, তাই এটি চর্বিতে দ্রবণীয় ভিটামিন, বিশেষ করে ভিটামিন A এর একটি উৎকৃষ্ট উৎস। ভিটামিন A দৃষ্টিশক্তি ও ত্বকের স্বাস্থ্যের জন্য অপরিহার্য। [MediX]"
    },
    {
        "question": "১৬৬। প্রতি শতগ্রাম মাখনে কত I.U পরিমাণ 'ভিটামিন-A' থাকে? [হাজারী স্যার]",
        "options": [
            "1000-2000",
            "2000-3000",
            "3000-4000",
            "3500-4000"
        ],
        "correct_option": 2,
        "explanation": "মাখন ভিটামিন A এর একটি সমৃদ্ধ উৎস। গরুর খাদ্যের উপর নির্ভর করে এর পরিমাণ পরিবর্তিত হলেও, প্রতি ১০০ গ্রাম মাখনে সাধারণত ৩০০০ থেকে ৪০০০ আন্তর্জাতিক একক (I.U) ভিটামিন A থাকে। [MediX]"
    },
    {
        "question": "১৬৭। কোনটি দুধের Osmole রূপে কাজ করে? [হাজারী স্যার]",
        "options": [
            "গ্লুকোজ",
            "ল্যাকটোজ",
            "গ্যালাক্টোজ",
            "ফ্রুক্টোজ"
        ],
        "correct_option": 1,
        "explanation": "অসমোল (Osmole) হলো কোনো দ্রবণের অভিস্রবণিক চাপ সৃষ্টিকারী কণা। দুধে প্রধানত ল্যাকটোজ এবং বিভিন্ন খনিজ লবণ অসমোল হিসেবে কাজ করে, যা দুধের সাথে রক্তরসের আইসোটনিক অবস্থা বজায় রাখতে সাহায্য করে। [MediX]"
    },
    {
        "question": "১৬৮। তাপ প্রয়োগে দুধকে জীবাণুমুক্ত করার প্রক্রিয়াকে কী বলে? [হাজারী স্যার]",
        "options": [
            "বিশুদ্ধকরণ",
            "পাস্তুরায়ন",
            "মন্থন",
            "ক্রিম ম্যাচুরেশন"
        ],
        "correct_option": 1,
        "explanation": "পাস্তুরায়ন বা পাস্তুরাইজেশন হলো একটি তাপীয় প্রক্রিয়া যেখানে দুধকে নির্দিষ্ট তাপমাত্রায় নির্দিষ্ট সময়ের জন্য উত্তপ্ত করে রোগ সৃষ্টিকারী অণুজীব ধ্বংস করা হয়। এটি দুধকে জীবাণুমুক্ত করার একটি বহুল প্রচলিত পদ্ধতি। [MediX]"
    },
    {
        "question": "১৬৯। নিচের কোনটি ক্যাজিনের প্রকারভেদ নয়? [হাজারী স্যার]",
        "options": [
            "αS1 ক্যাজিন",
            "αS2 ক্যাজিন",
            "β ক্যাজিন",
            "γ ক্যাজিন"
        ],
        "correct_option": 3,
        "explanation": "দুধের ক্যাসিন প্রোটিন মূলত চারটি প্রধান পলিপেপটাইড নিয়ে গঠিত: αS1-ক্যাসিন, αS2-ক্যাসিন, β-ক্যাসিন এবং κ-ক্যাসিন। গামা (γ) ক্যাসিন β-ক্যাসিনের প্রোটিওলাইটিক ফ্র্যাগমেন্ট থেকে উদ্ভূত হয়, তবে এটি মূল চারটি প্রকারের অন্তর্ভুক্ত নয়। [MediX]"
    },
    {
        "question": "১৭০। নিচের কোন ফ্যাটি এসিড বাটারের দুর্গন্ধের জন্য দায়ী? [কবীর স্যার]",
        "options": [
            "স্টিয়ারিক এসিড",
            "বিউটানয়িক এসিড",
            "অলিক এসিড",
            "লোরিক এসিড"
        ],
        "correct_option": 1,
        "explanation": "বাটার বা মাখন যখন পচে যায় (rancid), তখন এর ফ্যাট আর্দ্রবিশ্লেষিত হয়ে বিভিন্ন ফ্যাটি এসিড তৈরি করে। এর মধ্যে বিউটানয়িক এসিড (বা বিউটিরিক এসিড) এর গন্ধ অত্যন্ত তীব্র ও desagradable, যা পচা মাখনের দুর্গন্ধের জন্য প্রধানত দায়ী। [MediX]"
    },
    {
        "question": "১৭১। গ্রীষ্মকালে পাস্তুরায়নের পর শীতলীকরণের জন্য তাপমাত্রা কত? [গুহ স্যার]",
        "options": [
            "5-7°C",
            "7-10°C",
            "10-15°C",
            "10-12°C"
        ],
        "correct_option": 0,
        "explanation": "পাস্তুরায়ন প্রক্রিয়ায় দুধকে উত্তপ্ত করার পর দ্রুত ঠান্ডা করা একটি গুরুত্বপূর্ণ ধাপ। গ্রীষ্মকালে দুধকে দ্রুত ৫°C থেকে ৭°C তাপমাত্রায় নামিয়ে আনা হয়, যাতে তাপ-সহনশীল ব্যাকটেরিয়াগুলোর বৃদ্ধি রোধ করা যায়। [MediX]"
    },
    {
        "question": "১৭২। দুধের ক্রিম এবং ঘোল পরস্পর থেকে আলাদা করার প্রক্রিয়াকে কী বলে? [গুহ স্যার]",
        "options": [
            "পাস্তুরায়ন",
            "ক্রিম পৃথকীকরণ",
            "মন্থন",
            "ক্রিম ম্যাচুরেশন"
        ],
        "correct_option": 1,
        "explanation": "ক্রিম পৃথকীকরণ বা ক্রিম সেপারেশন হলো একটি যান্ত্রিক প্রক্রিয়া যেখানে সেন্ট্রিফিউগাল ফোর্স ব্যবহার করে দুধ থেকে হালকা ক্রিম (ফ্যাট) এবং ভারী স্কিম মিল্ক (ঘোল) আলাদা করা হয়। এই কাজে ব্যবহৃত যন্ত্রটিকে ক্রিম সেপারেটর বলে। [MediX]"
    },
    {
        "question": "১৭৩। হেয়ার ওয়েলের ইমালসিফায়ার (Emulsifier) রূপে নিচের কোনটি ব্যবহৃত হয়? [MAT: 18-19]",
        "options": [
            "ইথাইল অ্যালকোহল",
            "অলিক এসিড",
            "বিউটাইল হাইড্রো কুইনোন",
            "প্রোপাইল অ্যালকোহল"
        ],
        "correct_option": 1,
        "explanation": "হেয়ার অয়েল বা চুলের তেলে প্রায়শই তেল এবং জলীয় উপাদান মিশ্রিত থাকে। অলিক এসিডের মতো ফ্যাটি এসিডগুলো সারফেকট্যান্ট হিসেবে কাজ করে, যা তেল ও পানির মধ্যে পৃষ্ঠটান কমিয়ে একটি স্থিতিশীল ইমালশন তৈরি করতে সাহায্য করে। [MediX]"
    },
    {
        "question": "১৭৪। ভ্যানিশিং ক্রিমের প্রধান উপাদান কোনটি? [DAT: 18-19]",
        "options": [
            "টারটারিক এসিড",
            "আইসোপ্রোপাইল অ্যালকোহল",
            "স্টিয়ারিক এসিড",
            "ইথাইল বেনজয়েট"
        ],
        "correct_option": 2,
        "explanation": "ভ্যানিশিং ক্রিমের প্রধান উপাদান হলো স্টিয়ারিক এসিড। এটি পটাসিয়াম হাইড্রোক্সাইডের সাথে বিক্রিয়া করে পটাসিয়াম স্টিয়ারেট নামক সাবান তৈরি করে, যা তেল-ইন-ওয়াটার ইমালশন গঠন করে। এই ক্রিম ত্বকে লাগালে দ্রুত শোষিত হয়ে যায়, তাই একে ভ্যানিশিং ক্রিম বলে। [MediX]"
    },
    {
        "question": "১৭৫। টয়লেটের দূর্গন্ধ ও দাগ দূর করতে নিচের কোন রাসায়নিকটি ব্যবহৃত হয়? [DAT: 18-19]",
        "options": [
            "Ca(OH)₂",
            "NaOH",
            "Ca(OCl)₂",
            "C₆H₅OH"
        ],
        "correct_option": 2,
        "explanation": "Ca(OCl)₂ বা ক্যালসিয়াম হাইপোক্লোরাইট, যা ব্লিচিং পাউডার নামে পরিচিত, একটি শক্তিশালী জারক, বিরঞ্জক এবং জীবাণুনাশক। এটি টয়লেটের দাগ দূর করে, জীবাণু ধ্বংস করে এবং দুর্গন্ধ সৃষ্টিকারী যৌগগুলোকে জারিত করে দুর্গন্ধ দূর করে। [MediX]"
    },
    {
        "question": "১৭৬। বেবি পাউডারে এন্টিসেপ্টিক হিসাবে ব্যবহৃত হয় কোনটি? [MAT: 17-18]",
        "options": [
            "ক্যালসিয়াম অক্সাইড",
            "জিঙ্ক কার্বনেট",
            "বোরিক এসিড",
            "ক্যালসিয়াম কার্বনেট"
        ],
        "correct_option": 2,
        "explanation": "বেবি পাউডারে মৃদু এন্টিসেপটিক হিসেবে বোরিক এসিড (H₃BO₃) এর খুব সামান্য পরিমাণ ব্যবহার করা হয়। এটি ব্যাকটেরিয়ার বৃদ্ধি প্রতিহত করে ত্বককে সংক্রমণ থেকে রক্ষা করে। [MediX]"
    },
    {
        "question": "১৭৭। লিপস্টিকে ময়েশ্চারাইজার রূপে ব্যবহৃত হয় কোনটি? [DAT: 17-18]",
        "options": [
            "ইথাইল অ্যালকোহল",
            "গ্লিসারিন",
            "ইথিলিন গ্লাইকল",
            "আইসো প্রোপাইল অ্যালকোহল"
        ],
        "correct_option": 1,
        "explanation": "গ্লিসারিন একটি কার্যকর হিউমেকট্যান্ট (humectant), অর্থাৎ এটি বাতাস থেকে জলীয় বাষ্প শোষণ করে ত্বককে আর্দ্র রাখে। লিপস্টিকে এটি ময়েশ্চারাইজার হিসেবে ব্যবহৃত হয়, যা ঠোঁটকে শুষ্ক হওয়া থেকে রক্ষা করে। [MediX]"
    },
    {
        "question": "১৭৮। মেহেদীর রংয়ের জন্য দায়ী- [MAT: 16-17]",
        "options": [
            "ল্যানোলিন",
            "অলিক এসিড",
            "লোশন (Lotion)",
            "লাসোন (Lawsone)"
        ],
        "correct_option": 3,
        "explanation": "মেহেদি পাতার রঞ্জক পদার্থটির নাম হলো লাসোন (Lawsone)। এর রাসায়নিক নাম ২-হাইড্রোক্সি-১,৪-ন্যাপথাকুইনোন। এই যৌগটি ত্বকের কেরাটিন প্রোটিনের সাথে বিক্রিয়া করে লালচে-কমলা রঙের স্থায়ী দাগ তৈরি করে। [MediX]"
    },
    {
        "question": "১৭৯। কোল্ড ক্রিম প্রস্তুতিতে লুব্রিকেন্ট হিসেবে ব্যবহৃত হয় কোনটি? [DAT: 16-17]",
        "options": [
            "তরল প্যারাফিন",
            "গ্লিসারিন",
            "প্রোপাইল প্যারাফিন",
            "মোম"
        ],
        "correct_option": 0,
        "explanation": "কোল্ড ক্রিমে লুব্রিকেন্ট বা পিচ্ছিলকারক এবং ইমোলিয়েন্ট (emollient) হিসেবে তরল প্যারাফিন (liquid paraffin) বা খনিজ তেল ব্যবহার করা হয়। এটি ত্বকের উপর একটি পাতলা স্তর তৈরি করে আর্দ্রতা ধরে রাখে এবং ত্বককে মসৃণ করে। [MediX]"
    },
    {
        "question": "১৮০। বেকিং সোডার রাসায়নিক ফরমুলা কোনটি? [MAT: 15-16]",
        "options": [
            "Na₂CO₃·10H₂O",
            "Na₂CO₃",
            "NaOH",
            "NaHCO₃"
        ],
        "correct_option": 3,
        "explanation": "বেকিং সোডার রাসায়নিক নাম হলো সোডিয়াম বাইকার্বনেট বা সোডিয়াম হাইড্রোজেন কার্বনেট। এর রাসায়নিক সংকেত হলো NaHCO₃। এটি বেকিং পাউডারের একটি মূল উপাদান হিসেবে কেক বা পাউরুটি ফোলাতে ব্যবহৃত হয়। [MediX]"
    },
    {
        "question": "১৮১। ট্যালকম পাউডারের মূল উপাদান কোনটি? [হাজারী স্যার]",
        "options": [
            "ক্যালসিয়াম কার্বনেট",
            "বোরিক এসিড",
            "ট্যালক্",
            "ম্যাগনেসিয়াম কার্বনেট"
        ],
        "correct_option": 2,
        "explanation": "ট্যালকম পাউডারের মূল উপাদান হলো ট্যালক (Talc), যা একটি খনিজ পদার্থ। এর রাসায়নিক নাম হাইড্রেটেড ম্যাগনেসিয়াম সিলিকেট (3MgO·4SiO₂·H₂O)। এটি অত্যন্ত নরম এবং মসৃণ হওয়ায় পাউডার হিসেবে ব্যবহৃত হয়। [MediX]"
    },
    {
        "question": "১৮২। ট্যালকম পাউডার প্রস্তুতির মূল উপাদান হলো- [হাজারী স্যার]",
        "options": [
            "3MgO·4SiO₂·H₂O",
            "Na₂CO₃·10H₂O",
            "C₃H₈O₃",
            "CaCO₃·MgCO₃"
        ],
        "correct_option": 0,
        "explanation": "ট্যালকম পাউডারের মূল উপাদান ট্যালক এর রাসায়নিক সংকেত হলো 3MgO·4SiO₂·H₂O। এটি হাইড্রেটেড ম্যাগনেসিয়াম সিলিকেট নামে পরিচিত। [MediX]"
    },
    {
        "question": "১৮৩। লিপস্টিকের মূল উপাদান কোনটি? [হাজারী স্যার]",
        "options": [
            "মোম",
            "খনিজ তৈল",
            "রঞ্জক পদার্থ",
            "ভ্যাসলিন"
        ],
        "correct_option": 0,
        "explanation": "লিপস্টিকের মূল কাঠামো তৈরি হয় বিভিন্ন ধরনের মোম (Wax) যেমন- কার্নোবা মোম, মৌমাছির মোম ইত্যাদি দ্বারা। মোম লিপস্টিককে তার কঠিন গঠন এবং কাঠিন্য প্রদান করে, যা ঠোঁটে লাগানো সহজ করে। তেল, রঞ্জক পদার্থ ইত্যাদি মোমের ভিত্তিতে মিশ্রিত থাকে। [MediX]"
    },
    {
        "question": "১৮৪। টয়লেট ক্লিনারের প্রধান উপাদান কোনটি? [হাজারী স্যার]",
        "options": [
            "অ্যামোনিয়া",
            "কস্টিক সোডা",
            "স্পিরিট",
            "লবণ"
        ],
        "correct_option": 1,
        "explanation": "টয়লেট ক্লিনারে সাধারণত শক্তিশালী ক্ষার বা এসিড ব্যবহৃত হয়। দাগ ও ময়লা পরিষ্কারের জন্য কস্টিক সোডা (NaOH) বা শক্তিশালী এসিড (যেমন HCl) প্রধান উপাদান হিসেবে থাকে। কস্টিক সোডা চর্বি ও গ্রিজকে সাবানে পরিণত করে পরিষ্কার করে। [MediX]"
    },
    {
        "question": "১৮৫। কোনটি গ্লাস ক্লিনারের প্রধান উপাদান? [হাজারী স্যার]",
        "options": [
            "ভিনেগার",
            "অ্যাকুয়া অ্যামোনিয়া",
            "NaOH",
            "Na-লরাইল সালফেট"
        ],
        "correct_option": 1,
        "explanation": "গ্লাস ক্লিনারের প্রধান উপাদান হলো অ্যাকুয়া অ্যামোনিয়া বা অ্যামোনিয়ার জলীয় দ্রবণ (NH₄OH)। এটি কাঁচের পৃষ্ঠে থাকা গ্রিজ বা তৈলাক্ত ময়লাকে দ্রবীভূত করে এবং দ্রুত উবে যায় বলে কোনো দাগ বা রেখা ফেলে না। [MediX]"
    },
    {
        "question": "১৮৬। গ্লাস ক্লিনারে ব্যবহৃত রাবিং অ্যালকোহল নিচের কোনটি? [হাজারী স্যার]",
        "options": [
            "iso-প্রোপাইল অ্যালকোহল",
            "iso-বিউটাইল অ্যালকোহল",
            "tert-বিউটাইল অ্যালকোহল",
            "ইথাইল অ্যালকোহল"
        ],
        "correct_option": 0,
        "explanation": "গ্লাস ক্লিনারে দ্রাবক হিসেবে রাবিং অ্যালকোহল ব্যবহার করা হয়, যা মূলত আইসোপ্রোপাইল অ্যালকোহলের (Isopropyl alcohol) জলীয় দ্রবণ। এটি তেল-জাতীয় ময়লা দ্রবীভূত করতে সাহায্য করে এবং দ্রুত শুকিয়ে যায়। [MediX]"
    },
    {
        "question": "১৮৭। নেইল পলিশ এর দ্রাবক কোনটি? [হাজারী স্যার]",
        "options": [
            "ইথানোয়িক এসিড",
            "ইথাইল ইথানোয়েট",
            "ইথাইল অ্যালকোহল",
            "কার্বক্সিলিক এসিড"
        ],
        "correct_option": 1,
        "explanation": "নেইল পলিশে বিভিন্ন উপাদান যেমন নাইট্রোসেলুলোজকে দ্রবীভূত করার জন্য এস্টার জাতীয় দ্রাবক ব্যবহৃত হয়। ইথাইল ইথানোয়েট (বা ইথাইল অ্যাসিটেট) একটি বহুল ব্যবহৃত দ্রাবক যা নেইল পলিশে ব্যবহৃত হয়। [MediX]"
    },
    {
        "question": "১৮৮। মেহেদি পাতার নির্যাসে কোন যৌগটির প্রাধান্য থাকে? [হাজারী স্যার]",
        "options": [
            "2-হাইড্রোক্সি বেনজো কুইনোন",
            "বেনজো কুইনোন",
            "2-হাইড্রোক্সি 1,4-ন্যাপথা কুইনোন",
            "ডায়াজোনিয়াম ক্লোরাইড"
        ],
        "correct_option": 2,
        "explanation": "মেহেদি পাতার নির্যাসে প্রধানত 'লাসোন' (Lawsone) নামক একটি রঞ্জক পদার্থ থাকে। এর রাসায়নিক নাম হলো ২-হাইড্রোক্সি-১,৪-ন্যাপথাকুইনোন, যা ত্বকের প্রোটিনের সাথে যুক্ত হয়ে লালচে রঙ তৈরি করে। [MediX]"
    },
    {
        "question": "১৮৯। বিষনাশক ও জীবাণুনাশক কোনটি? [কবীর স্যার]",
        "options": [
            "লেসিথিন",
            "গোলাপজল",
            "মেনথল",
            "অ্যালোভেরা"
        ],
        "correct_option": 3,
        "explanation": "অ্যালোভেরা বা ঘৃতকুমারীর নির্যাসে বিভিন্ন ধরনের রাসায়নিক উপাদান থাকে যার মধ্যে কিছু উপাদানের এন্টিসেপটিক বা জীবাণুনাশক বৈশিষ্ট্য রয়েছে। এটি ত্বকের ক্ষত ও পোড়া নিরাময়ে সাহায্য করে। [MediX]"
    },
    {
        "question": "১৯০। গ্রিজ অপসারণের জন্য টয়লেট ক্লিনারে ব্যবহার করা হয় নিম্নের কোনটি? [কবীর স্যার]",
        "options": [
            "NaOH",
            "CH₃COOH",
            "NH₄OH",
            "HNO₃"
        ],
        "correct_option": 0,
        "explanation": "সোডিয়াম হাইড্রোক্সাইড (NaOH) একটি শক্তিশালী ক্ষার। এটি গ্রিজ বা চর্বির (যা মূলত এস্টার) সাথে স্যাপোনিফিকেশন বিক্রিয়া করে সাবান ও গ্লিসারল তৈরি করে। উৎপন্ন সাবান পানিতে দ্রবণীয় হওয়ায় গ্রিজ সহজে অপসারিত হয়। [MediX]"
    },
    {
        "question": "১৯১। ট্যালক কী? [কবীর স্যার]",
        "options": [
            "সোডিয়াম সিলিকেট",
            "ম্যাগনেসিয়াম সিলিকেট",
            "পটাসিয়াম সিলিকেট",
            "অ্যালুমিনিয়াম সিলিকেট"
        ],
        "correct_option": 1,
        "explanation": "ট্যালক হলো একটি খনিজ পদার্থ যার রাসায়নিক নাম হাইড্রেটেড ম্যাগনেসিয়াম সিলিকেট (Hydrated Magnesium Silicate)। এর রাসায়নিক সংকেত Mg₃Si₄O₁₀(OH)₂ বা 3MgO·4SiO₂·H₂O। [MediX]"
    },
    {
        "question": "১৯২। উচ্চতর ফ্যাটি এসিডের সোডিয়াম লবণ হলো- [কবীর স্যার]",
        "options": [
            "গ্লিসারিন",
            "ডিটারজেন্ট",
            "ব্লিচিং পাউডার",
            "সাবান"
        ],
        "correct_option": 3,
        "explanation": "সাবান হলো উচ্চতর ফ্যাটি এসিড (যেমন- স্টিয়ারিক এসিড, পামিটিক এসিড) এর সোডিয়াম বা পটাসিয়াম লবণ। তেল বা চর্বিকে ক্ষার (NaOH বা KOH) দ্বারা আর্দ্রবিশ্লেষণ করে সাবান প্রস্তুত করা হয়। [MediX]"
    },
    {
        "question": "১৯৩। নিচের কোনটি প্রস্তুতিতে স্টিয়ারিক এসিড লাগে? [কবীর স্যার]",
        "options": [
            "স্নো",
            "কোল্ড ক্রিম",
            "ট্যালকম পাউডার",
            "লিপস্টিক"
        ],
        "correct_option": 0,
        "explanation": "স্নো বা ভ্যানিশিং ক্রিম প্রস্তুতিতে স্টিয়ারিক এসিড একটি অপরিহার্য উপাদান। এটি ক্ষারের সাথে বিক্রিয়া করে সাবান তৈরি করে যা তেল-ইন-ওয়াটার (O/W) ইমালশনের ভিত্তি হিসেবে কাজ করে। [MediX]"
    },
    {
        "question": "১৯৪। ট্যালকের সংযুক্তি কোনটি? [গুহ স্যার]",
        "options": [
            "4MgO·3SiO₂·H₂O",
            "3MgO·4SiO₂·H₂O",
            "3MgO·SiO₂·4H₂O",
            "4MgO·2SiO₂·H₂O"
        ],
        "correct_option": 1,
        "explanation": "ট্যালক খনিজের রাসায়নিক সংযুক্তি হলো হাইড্রেটেড ম্যাগনেসিয়াম সিলিকেট, যার আদর্শ সংকেত 3MgO·4SiO₂·H₂O বা Mg₃Si₄O₁₀(OH)₂। [MediX]"
    },
    {
        "question": "১৯৫। ভ্যানিশিং ক্রিমের প্রধান উপাদান কোনটি? [গুহ স্যার]",
        "options": [
            "কস্টিক পটাশ",
            "স্টিয়ারিক এসিড",
            "অলিভ অয়েল",
            "সরবিটল"
        ],
        "correct_option": 1,
        "explanation": "ভ্যানিশিং ক্রিমের মূল উপাদান হলো স্টিয়ারিক এসিড। এটি ক্রিমের ভিত্তি তৈরি করে এবং ত্বকে একটি ম্যাট ফিনিশ দেয়। কস্টিক পটাশ (KOH) ইমালসিফায়ার (সাবান) তৈরির জন্য ব্যবহৃত হয়। [MediX]"
    },
    {
        "question": "১৯৬। বেবী পাউডার প্রস্তুতির মূল উপাদান- [গুহ স্যার]",
        "options": [
            "C₃H₈O₃",
            "CaCO₃·MgCO₃",
            "3MgO·4SiO₂·H₂O",
            "Na₂CO₃·10H₂O"
        ],
        "correct_option": 2,
        "explanation": "বেবি পাউডার বা ট্যালকম পাউডার প্রস্তুতির মূল উপাদান হলো ট্যালক, যার রাসায়নিক সংকেত 3MgO·4SiO₂·H₂O (হাইড্রেটেড ম্যাগনেসিয়াম সিলিকেট)। [MediX]"
    },
    {
        "question": "১৯৭। নিচের কোনটি ময়েশ্চারাইজাররূপে আফটার শেভ লোশানে ব্যবহৃত হয়? [গুহ স্যার]",
        "options": [
            "ডি-ন্যাচার্ড অ্যালকোহল",
            "প্রোপাইলিন গ্লাইকল",
            "ইথিলিন গ্লাইকল",
            "গ্লিসারল"
        ],
        "correct_option": 3,
        "explanation": "আফটার শেভ লোশানে গ্লিসারল বা গ্লিসারিন ময়েশ্চারাইজার হিসেবে ব্যবহৃত হয়। এটি একটি হিউমেকট্যান্ট যা ত্বককে আর্দ্র রাখে এবং শেভিং এর ফলে সৃষ্ট শুষ্কতা ও জ্বালাপোড়া কমাতে সাহায্য করে। অ্যালকোহল এন্টিসেপটিক হিসেবে কাজ করে। [MediX]"
    },
    {
        "question": "১৯৮। কোনটি টয়লেট ক্লিনারের মূল উপাদান? [গুহ স্যার]",
        "options": [
            "NaOH",
            "NH₄OH",
            "Ca(OCl)Cl",
            "KOH"
        ],
        "correct_option": 0,
        "explanation": "শক্তিশালী টয়লেট ক্লিনারগুলোতে মূল উপাদান হিসেবে কস্টিক সোডা (NaOH) বা হাইড্রোক্লোরিক এসিড (HCl) ব্যবহৃত হয়। NaOH একটি শক্তিশালী ক্ষার যা গ্রিজ, চর্বি ও অন্যান্য জৈব ময়লা দ্রবীভূত করে পরিষ্কার করে। Ca(OCl)Cl (ব্লিচিং পাউডার) জীবাণুনাশক হিসেবে কাজ করে। [MediX]"
    },
    {
        "question": "১৯৯। প্রসাধন সামগ্রীতে সুগন্ধি উপাদান হিসেবে ব্যবহৃত হয়- [লিংকন স্যার]",
        "options": [
            "জেরানিওল",
            "লাসোন",
            "সোডিয়াম সরবেট",
            "টকোফেরল"
        ],
        "correct_option": 0,
        "explanation": "জেরানিওল (Geraniol) হলো একটি অ্যালকোহল যা গোলাপ, জেরানিয়াম এবং লেমনগ্রাস থেকে পাওয়া যায়। এর মনোরম সুগন্ধের জন্য এটি পারফিউম, লোশন, সাবান এবং অন্যান্য প্রসাধন সামগ্রীতে বহুল ব্যবহৃত হয়। [MediX]"
    },
    {
        "question": "২০০। Moisturizing cream প্রস্তুতিতে ব্যবহৃত হয় কোনটি? [হাজারী স্যার]",
        "options": [
            "কাইটিন",
            "ইথার",
            "হেক্সেন-1, 3, 4, 6-টেট্রাঅল",
            "ফেনল"
        ],
        "correct_option": 2,
        "explanation": "ময়েশ্চারাইজিং ক্রিমে হিউমেকট্যান্ট (আর্দ্রতা আকর্ষণকারী) হিসেবে বিভিন্ন পলিহাইড্রোক্সি অ্যালকোহল ব্যবহৃত হয়। হেক্সেন-1, 3, 4, 6-টেট্রাঅল এই ধরনের একটি যৌগ যা ত্বকের আর্দ্রতা ধরে রাখতে সাহায্য করে। [MediX]"
    }
]
